fastflowtransform/__init__.py
fastflowtransform/_version.py
fastflowtransform/artifacts.py
fastflowtransform/cache.py
fastflowtransform/core.py
fastflowtransform/dag.py
fastflowtransform/decorators.py
fastflowtransform/docs.py
fastflowtransform/errors.py
fastflowtransform/fingerprint.py
fastflowtransform/incremental.py
fastflowtransform/lineage.py
fastflowtransform/log_queue.py
fastflowtransform/logging.py
fastflowtransform/meta.py
fastflowtransform/packages.py
fastflowtransform/run_executor.py
fastflowtransform/schema_loader.py
fastflowtransform/seeding.py
fastflowtransform/settings.py
fastflowtransform/source_freshness.py
fastflowtransform/storage.py
fastflowtransform/streaming.py
fastflowtransform/typing.py
fastflowtransform/utest.py
fastflowtransform/validation.py
fastflowtransform/api/__init__.py
fastflowtransform/api/context.py
fastflowtransform/api/http.py
fastflowtransform/api/rate_limit.py
fastflowtransform/ci/__init__.py
fastflowtransform/ci/changed_since.py
fastflowtransform/ci/core.py
fastflowtransform/ci/sarif.py
fastflowtransform/cli/__init__.py
fastflowtransform/cli/__main__.py
fastflowtransform/cli/bootstrap.py
fastflowtransform/cli/ci_cmd.py
fastflowtransform/cli/dag_cmd.py
fastflowtransform/cli/deps_cmd.py
fastflowtransform/cli/docgen_cmd.py
fastflowtransform/cli/docs_cmd.py
fastflowtransform/cli/docs_utils.py
fastflowtransform/cli/init_cmd.py
fastflowtransform/cli/logging_utils.py
fastflowtransform/cli/options.py
fastflowtransform/cli/run.py
fastflowtransform/cli/seed_cmd.py
fastflowtransform/cli/selectors.py
fastflowtransform/cli/snapshot_cmd.py
fastflowtransform/cli/source_cmd.py
fastflowtransform/cli/sync_db_comments_cmd.py
fastflowtransform/cli/test_cmd.py
fastflowtransform/cli/utest_cmd.py
fastflowtransform/config/__init__.py
fastflowtransform/config/budgets.py
fastflowtransform/config/contracts.py
fastflowtransform/config/loaders.py
fastflowtransform/config/models.py
fastflowtransform/config/packages.py
fastflowtransform/config/project.py
fastflowtransform-0.6.14.dist-info/METADATA
fastflowtransform-0.6.14.dist-info/WHEEL
fastflowtransform-0.6.14.dist-info/entry_points.txt
fastflowtransform-0.6.14.dist-info/RECORD
