Metadata-Version: 2.4
Name: fastflowtransform
Version: 0.6.14
Summary: Python framework for SQL & Python data transformation, ETL pipelines, and dbt-style data modeling
Project-URL: Homepage, https://github.com/MirrorsAndMisdirections/FastFlowTransform
Project-URL: Documentation, https://fastflowtransform.com
Project-URL: Repository, https://github.com/MirrorsAndMisdirections/FastFlowTransform.git
Project-URL: Source, https://github.com/MirrorsAndMisdirections/fastflowtransform
Project-URL: Issues, https://github.com/MirrorsAndMisdirections/fastflowtransform/issues
Author: Marko Lekic
License: Apache-2.0
Keywords: bigquery,data modeling,data transformation,dbt alternative,duckdb,etl,postgres,snowflake,spark,sql
Classifier: Intended Audience :: Developers
Classifier: License :: OSI Approved :: Apache Software License
Classifier: Operating System :: OS Independent
Classifier: Programming Language :: Python :: 3
Classifier: Topic :: Database
Classifier: Topic :: Scientific/Engineering :: Information Analysis
Classifier: Topic :: Software Development :: Build Tools
Classifier: Topic :: Software Development :: Libraries
Requires-Python: >=3.12
Requires-Dist: duckdb>=1.0
Requires-Dist: httpx>=0.28.1
Requires-Dist: jinja2>=3.1
Requires-Dist: pandas>=2.0
Requires-Dist: pydantic-settings>=2.4
Requires-Dist: pydantic>=2.8
Requires-Dist: python-dotenv>=1.0
Requires-Dist: pyyaml>=6.0
Requires-Dist: sqlalchemy>=2.0
Requires-Dist: typer>=0.12
Provides-Extra: bigquery
Requires-Dist: google-cloud-bigquery>=3.25; extra == 'bigquery'
Provides-Extra: bigquery-bf
Requires-Dist: bigframes>=2.24.0; extra == 'bigquery-bf'
Requires-Dist: google-cloud-bigquery>=3.25; extra == 'bigquery-bf'
Provides-Extra: dev
Requires-Dist: mypy==1.18.*; extra == 'dev'
Requires-Dist: pandas-stubs>=2.1; extra == 'dev'
Requires-Dist: pre-commit==3.*; extra == 'dev'
Requires-Dist: pytest-cov==7.0.*; extra == 'dev'
Requires-Dist: pytest-rerunfailures==14.0.*; extra == 'dev'
Requires-Dist: pytest==8.4.*; extra == 'dev'
Requires-Dist: ruff==0.14.*; extra == 'dev'
Requires-Dist: types-pyyaml>=6.0.12; extra == 'dev'
Provides-Extra: docs
Requires-Dist: mkdocs-autorefs>=1.0; extra == 'docs'
Requires-Dist: mkdocs-gen-files>=0.5; extra == 'docs'
Requires-Dist: mkdocs-literate-nav>=0.6; extra == 'docs'
Requires-Dist: mkdocs-material>=9.5; extra == 'docs'
Requires-Dist: mkdocs-section-index>=0.3; extra == 'docs'
Requires-Dist: mkdocs>=1.6; extra == 'docs'
Requires-Dist: mkdocstrings[python]>=0.25; extra == 'docs'
Requires-Dist: pymdown-extensions>=10.0; extra == 'docs'
Provides-Extra: full
Requires-Dist: bigframes>=2.24.0; extra == 'full'
Requires-Dist: delta-spark>=4.0.0; extra == 'full'
Requires-Dist: google-cloud-bigquery>=3.25; extra == 'full'
Requires-Dist: psycopg2-binary>=2.9; extra == 'full'
Requires-Dist: psycopg[binary]>=3.1; extra == 'full'
Requires-Dist: pyspark>=4.0.1; extra == 'full'
Requires-Dist: snowflake-connector-python>=4.0.0; extra == 'full'
Requires-Dist: snowflake-snowpark-python>=1.40.0; extra == 'full'
Provides-Extra: postgres
Requires-Dist: psycopg2-binary>=2.9; extra == 'postgres'
Requires-Dist: psycopg[binary]>=3.1; extra == 'postgres'
Provides-Extra: snowflake
Requires-Dist: snowflake-connector-python>=4.0.0; extra == 'snowflake'
Requires-Dist: snowflake-snowpark-python>=1.40.0; extra == 'snowflake'
Provides-Extra: spark
Requires-Dist: delta-spark>=4.0.0; extra == 'spark'
Requires-Dist: pyspark>=4.0.1; extra == 'spark'
